short_text_tagger
