Metadata-Version: 1.2
Name: short-text-tagger
Version: 0.1.7
Summary: Short-text tagger generates topic distributions for all texts in a corpus.
Home-page: https://github.com/JohnAnthonyBowllan/short_text_tagger
Author: John Anthony Bowllan
Author-email: jbowllan@gmail.com
License: MIT license
Keywords: short_text_tagger
Platform: UNKNOWN
Classifier: Development Status :: 2 - Pre-Alpha
Classifier: Intended Audience :: Developers
Classifier: License :: OSI Approved :: MIT License
Classifier: Natural Language :: English
Classifier: Programming Language :: Python :: 3
Classifier: Programming Language :: Python :: 3.5
Classifier: Programming Language :: Python :: 3.6
Classifier: Programming Language :: Python :: 3.7
Classifier: Programming Language :: Python :: 3.8
Requires-Python: >=3.5
